bskyapi/__init__.py
bskyapi/clients.py
bskyapi/scrapers/__init__.py
bskyapi/scrapers/profile.py
bskyapi/scrapers/search_term.py
bskyapi/storage/__init__.py
bskyapi/storage/writers.py
bskyapi-0.2.1.dist-info/LICENSE
bskyapi-0.2.1.dist-info/METADATA
bskyapi-0.2.1.dist-info/WHEEL
bskyapi-0.2.1.dist-info/RECORD
