Metadata-Version: 2.1
Name: bskyapi
Version: 0.2.1
Summary: 
Home-page: https://github.com/stoltzmaniac/bskyapi
License: Apache 2.0
Keywords: bluesky,bsky,api,wrapper,atproto
Author: Scott Stoltzman
Author-email: scottstoltzman@gmail.com
Requires-Python: >=3.11,<3.14
Classifier: License :: Other/Proprietary License
Classifier: Programming Language :: Python :: 3
Classifier: Programming Language :: Python :: 3.11
Classifier: Programming Language :: Python :: 3.12
Classifier: Programming Language :: Python :: 3.13
Requires-Dist: atproto (>=0.0.56,<0.0.57)
Requires-Dist: python-dotenv (>=1.0.1,<2.0.0)
Project-URL: Repository, https://github.com/stoltzmaniac/bskyapi
